{
	"root":"map",
	"extra":[
		{
			"name":"text",
			"type":"UTF"
		},
		{
			"name":"x",
			"type":"Int"
		},
		{
			"name":"y",
			"type":"Int"
		}
	],
	"thing":[
		{
			"name":"s1",
			"type":"Short"
		},
		{
			"name":"text",
			"type":"UTF"
		},
		{
			"name":"arraySize1",
			"type":"Short"
		},
		{
			"name":"shortArray1",
			"type":"array",
			"arrayType":"Short",
			"arrayLengthLookup":"arraySize1"
		},
		{
			"name":"arraySize2",
			"type":"Short"
		},
		{
			"name":"shortArray2",
			"type":"array",
			"arrayType":"Short",
			"arrayLengthLookup":"arraySize2"
		},
		{
			"name":"arraySize3",
			"type":"Short"
		},
		{
			"name":"shortArray3",
			"type":"array",
			"arrayType":"Short",
			"arrayLengthLookup":"arraySize3"
		},
		{
			"name":"arraySize4",
			"type":"Short"
		},
		{
			"name":"shortArray4",
			"type":"array",
			"arrayType":"Short",
			"arrayLengthLookup":"arraySize4"
		},
		{
			"name":"arraySize5",
			"type":"Short"
		},
		{
			"name":"shortArray5",
			"type":"array",
			"arrayType":"Short",
			"arrayLengthLookup":"arraySize5"
		},
		{
			"name":"arraySize6",
			"type":"Short"
		},
		{
			"name":"shortArray6",
			"type":"array",
			"arrayType":"Short",
			"arrayLengthLookup":"arraySize6"
		},
		{
			"name":"arraySize7",
			"type":"Short"
		},
		{
			"name":"shortArray7",
			"type":"array",
			"arrayType":"Short",
			"arrayLengthLookup":"arraySize7"
		},
		{
			"name":"arraySize8",
			"type":"Short"
		},
		{
			"name":"shortArray8",
			"type":"array",
			"arrayType":"Short",
			"arrayLengthLookup":"arraySize8"
		}
	],
	"entity":[
		{
			"name":"id",
			"type":"Short"
		},
		{
			"name":"x",
			"type":"Float"
		},
		{
			"name":"y",
			"type":"Float"
		},
		{
			"name":"script",
			"type":"Short"
		},
		{
			"name":"parameterSize",
			"type":"Short",
			"dependsOn":"script"
		},
		{
			"name":"parameters",
			"type":"array",
			"arrayType":"Byte",
			"arrayLengthLookup":"parameterSize",
			"dependsOn":"script"
		}
	],
	"treasure":[
		{
			"name":"id",
			"type":"Short"
		},
		{
			"name":"x",
			"type":"Float"
		},
		{
			"name":"y",
			"type":"Float"
		}
	],
	"door":[
		{
			"name":"id",
			"type":"Short"
		},
		{
			"name":"display",
			"type":"Short"
		},
		{
			"name":"cover",
			"type":"Short"
		},
		{
			"name":"triggerArea",
			"type":"Short"
		},
		{
			"name":"barrier",
			"type":"Short"
		}
	],
	"enemySpawn":[
		{
			"name":"id",
			"type":"Short"
		},
		{
			"name":"x",
			"type":"Float"
		},
		{
			"name":"y",
			"type":"Float"
		},
		{
			"name":"script",
			"type":"Short"
		},
		{
			"name":"parameterSize",
			"type":"Short",
			"dependsOn":"script"
		},
		{
			"name":"parameters",
			"type":"array",
			"arrayType":"Byte",
			"arrayLengthLookup":"parameterSize",
			"dependsOn":"script"
		}

	],
	"avatarSpawn":[
		{
			"name":"id",
			"type":"Short"
		},
		{
			"name":"x",
			"type":"Float"
		},
		{
			"name":"y",
			"type":"Float"
		}
	],
	"graph":[
		{
			"name":"id",
			"type":"Short"
		},
		{
			"name":"nodeCount",
			"type":"Short"
		},
		{
			"name":"nodes",
			"type":"array",
			"arrayType":"Short",
			"arrayLengthLookup":"nodeCount"
		}
	],
	"edge":[
		{
			"name":"a",
			"type":"Short"
		},
		{
			"name":"b",
			"type":"Short"
		},
		{
			"name":"weight",
			"type":"Float"
		}
	],
	"node":[
		{
			"name":"id",
			"type":"Short"
		},
		{
			"name":"x",
			"type":"Float"
		},
		{
			"name":"y",
			"type":"Float"
		},
		{
			"name":"name",
			"type":"UTF"
		}
	],
	"tile":[
		{
			"name":"id",
			"type":"Short"
		},
		{
			"name":"image",
			"type":"Short"
		},
		{
			"name":"z",
			"type":"Float"
		},
		{
			"name":"isInBottomLayer",
			"type":"Boolean"
		},
		{
			"name":"isCollapsed",
			"type":"Boolean"
		},
		{
			"name":"x",
			"type":"Float"
		},
		{
			"name":"y",
			"type":"Float"
		},
		{
			"name":"rotation",
			"type":"Float"
		},
		{
			"name":"scaleX",
			"type":"Float"
		},
		{
			"name":"scaleY",
			"type":"Float"
		},
		{
			"name":"b1",
			"type":"Boolean"
		},
		{
			"name":"b2",
			"type":"Boolean"
		},
		{
			"name":"s1",
			"type":"Short"
		},
		{
			"name":"s2",
			"type":"Short"
		}
	],
	"map":[
		{
			"name":"id",
			"type":"Short"
		},
		{
			"name":"tileCount",
			"type":"Short"
		},
		{
			"name":"tiles",
			"type":"lookup",
			"lookupId":"tile",
			"lengthId":"tileCount"
		},
		{
			"name":"nodeCount",
			"type":"Short"
		},
		{
			"name":"nodes",
			"type":"lookup",
			"lookupId":"node",
			"lengthId":"nodeCount"
		},
		{
			"name":"edgeCount",
			"type":"Short"
		},
		{
			"name":"edges",
			"type":"lookup",
			"lookupId":"edge",
			"lengthId":"edgeCount"
		},
		{
			"name":"graphCount",
			"type":"Short"
		},
		{
			"name":"graphs",
			"type":"lookup",
			"lookupId":"graph",
			"lengthId":"graphCount"
		},
		{
			"name":"physicsCount",
			"type":"Short"
		},
		{
			"name":"physicsEdgeGraphs",
			"type":"array",
			"arrayType":"Short",
			"arrayLengthLookup":"physicsCount"
		},
		{
			"name":"aiCount",
			"type":"Short"
		},
		{
			"name":"aiPathingGraphs",
			"type":"array",
			"arrayType":"Short",
			"arrayLengthLookup":"aiCount"
		},
		{
			"name":"avatarSpawnCount",
			"type":"Short"
		},
		{
			"name":"avatarSpawns",
			"type":"lookup",
			"lookupId":"avatarSpawn",
			"lengthId":"avatarSpawnCount"
		},
		{
			"name":"enemySpawnCount",
			"type":"Short"
		},
		{
			"name":"enemySpawns",
			"type":"lookup",
			"lookupId":"enemySpawn",
			"lengthId":"enemySpawnCount"
		},
		{
			"name":"doorCount",
			"type":"Short"
		},
		{
			"name":"doors",
			"type":"lookup",
			"lookupId":"door",
			"lengthId":"doorCount"
		},
		{
			"name":"treasureCount",
			"type":"Short"
		},
		{
			"name":"treasures",
			"type":"lookup",
			"lookupId":"treasure",
			"lengthId":"treasureCount"
		},
		{
			"name":"entityCount",
			"type":"Short"
		},
		{
			"name":"entities",
			"type":"lookup",
			"lookupId":"entity",
			"lengthId":"entityCount"
		},
		{
			"name":"thingCount",
			"type":"Byte"
		},
		{
			"name":"things",
			"type":"lookup",
			"lookupId":"thing",
			"lengthId":"thingCount"
		},
		{
			"name":"extraCount",
			"type":"Short"
		},
		{
			"name":"extras",
			"type":"lookup",
			"lookupId":"extra",
			"lengthId":"extraCount"
		}
	]
}
